[{"date":"2025-10-22","opp":"POR","result":"W, 118-114","pts":2,"reb":4,"ast":3,"stl":2,"blk":0,"tov":1,"tpm":0,"fg_pct":0.2,"ft_pct":null},{"date":"2025-10-24","opp":"LAL","result":"L, 110-128","pts":9,"reb":3,"ast":1,"stl":0,"blk":0,"tov":0,"tpm":1,"fg_pct":0.6,"ft_pct":1},{"date":"2025-10-26","opp":"IND","result":"W, 114-110","pts":6,"reb":2,"ast":0,"stl":1,"blk":0,"tov":0,"tpm":0,"fg_pct":0.5,"ft_pct":1},{"date":"2025-11-01","opp":"CHO","result":"W, 122-105","pts":6,"reb":1,"ast":0,"stl":1,"blk":0,"tov":0,"tpm":0,"fg_pct":0.5,"ft_pct":null},{"date":"2025-11-03","opp":"BRK","result":"W, 125-109","pts":2,"reb":5,"ast":2,"stl":0,"blk":0,"tov":1,"tpm":0,"fg_pct":0.333,"ft_pct":0},{"date":"2025-11-05","opp":"NYK","result":"L, 114-137","pts":3,"reb":1,"ast":0,"stl":1,"blk":0,"tov":0,"tpm":1,"fg_pct":0.5,"ft_pct":null},{"date":"2025-11-07","opp":"UTA","result":"W, 137-97","pts":6,"reb":1,"ast":2,"stl":2,"blk":1,"tov":0,"tpm":1,"fg_pct":0.5,"ft_pct":0.5},{"date":"2025-11-09","opp":"SAC","result":"W, 144-117","pts":11,"reb":2,"ast":1,"stl":0,"blk":0,"tov":1,"tpm":3,"fg_pct":0.75,"ft_pct":1},{"date":"2025-11-10","opp":"UTA","result":"W, 120-113","pts":2,"reb":1,"ast":0,"stl":1,"blk":0,"tov":1,"tpm":0,"fg_pct":0.5,"ft_pct":null},{"date":"2025-11-14","opp":"SAC","result":"W, 124-110","pts":5,"reb":1,"ast":0,"stl":1,"blk":0,"tov":0,"tpm":0,"fg_pct":0.2,"ft_pct":0.75},{"date":"2025-11-15","opp":"DEN","result":"L, 112-123","pts":3,"reb":2,"ast":0,"stl":0,"blk":0,"tov":1,"tpm":1,"fg_pct":1,"ft_pct":null},{"date":"2025-11-17","opp":"DAL","result":"W, 120-96","pts":5,"reb":6,"ast":0,"stl":1,"blk":0,"tov":0,"tpm":1,"fg_pct":0.4,"ft_pct":null},{"date":"2025-11-19","opp":"WAS","result":"W, 120-109","pts":7,"reb":5,"ast":0,"stl":3,"blk":1,"tov":0,"tpm":1,"fg_pct":0.429,"ft_pct":0},{"date":"2025-11-21","opp":"PHO","result":"L, 113-114","pts":1,"reb":3,"ast":0,"stl":1,"blk":0,"tov":0,"tpm":0,"fg_pct":0,"ft_pct":0.5},{"date":"2025-11-24","opp":"SAC","result":"L, 112-117 (OT)","pts":0,"reb":3,"ast":0,"stl":0,"blk":0,"tov":0,"tpm":0,"fg_pct":0,"ft_pct":null},{"date":"2025-11-26","opp":"OKC","result":"L, 105-113","pts":0,"reb":0,"ast":0,"stl":0,"blk":0,"tov":1,"tpm":0,"fg_pct":0,"ft_pct":null},{"date":"2025-11-29","opp":"BOS","result":"W, 119-115","pts":0,"reb":1,"ast":0,"stl":0,"blk":0,"tov":0,"tpm":0,"fg_pct":0,"ft_pct":null},{"date":"2025-11-30","opp":"SAS","result":"W, 125-112","pts":8,"reb":0,"ast":0,"stl":1,"blk":0,"tov":0,"tpm":2,"fg_pct":1,"ft_pct":1},{"date":"2025-12-02","opp":"NOP","result":"W, 149-142 (OT)","pts":6,"reb":2,"ast":0,"stl":0,"blk":0,"tov":0,"tpm":2,"fg_pct":0.5,"ft_pct":null},{"date":"2025-12-04","opp":"NOP","result":"W, 125-116","pts":12,"reb":2,"ast":0,"stl":1,"blk":0,"tov":0,"tpm":2,"fg_pct":0.444,"ft_pct":1},{"date":"2025-12-06","opp":"LAC","result":"W, 109-106","pts":8,"reb":3,"ast":0,"stl":1,"blk":0,"tov":0,"tpm":0,"fg_pct":0.6,"ft_pct":1},{"date":"2025-12-08","opp":"PHO","result":"L, 105-108","pts":3,"reb":2,"ast":1,"stl":0,"blk":0,"tov":0,"tpm":0,"fg_pct":0.5,"ft_pct":0.5},{"date":"2025-12-12","opp":"GSW","result":"W, 127-120","pts":2,"reb":1,"ast":2,"stl":2,"blk":0,"tov":0,"tpm":0,"fg_pct":0.333,"ft_pct":0},{"date":"2025-12-14","opp":"SAC","result":"W, 117-103","pts":2,"reb":1,"ast":0,"stl":0,"blk":0,"tov":2,"tpm":0,"fg_pct":0.333,"ft_pct":null},{"date":"2025-12-17","opp":"MEM","result":"L, 110-116","pts":2,"reb":1,"ast":0,"stl":1,"blk":1,"tov":1,"tpm":0,"fg_pct":0.25,"ft_pct":null},{"date":"2025-12-21","opp":"MIL","result":"W, 103-100","pts":0,"reb":0,"ast":0,"stl":1,"blk":0,"tov":0,"tpm":0,"fg_pct":0,"ft_pct":null},{"date":"2025-12-23","opp":"NYK","result":"W, 115-104","pts":5,"reb":1,"ast":3,"stl":0,"blk":0,"tov":2,"tpm":1,"fg_pct":1,"ft_pct":0},{"date":"2025-12-25","opp":"DEN","result":"L, 138-142 (OT)","pts":2,"reb":0,"ast":0,"stl":0,"blk":0,"tov":0,"tpm":0,"fg_pct":0.5,"ft_pct":null},{"date":"2025-12-27","opp":"BRK","result":"L, 107-123","pts":6,"reb":2,"ast":0,"stl":0,"blk":0,"tov":0,"tpm":0,"fg_pct":0.25,"ft_pct":0.8},{"date":"2025-12-29","opp":"CHI","result":"W, 136-101","pts":11,"reb":4,"ast":0,"stl":3,"blk":1,"tov":0,"tpm":0,"fg_pct":0.571,"ft_pct":1},{"date":"2025-12-31","opp":"ATL","result":"L, 102-126","pts":3,"reb":0,"ast":0,"stl":1,"blk":1,"tov":1,"tpm":0,"fg_pct":0.25,"ft_pct":0.5},{"date":"2026-01-03","opp":"MIA","result":"W, 125-115","pts":2,"reb":0,"ast":0,"stl":0,"blk":0,"tov":0,"tpm":0,"fg_pct":0.5,"ft_pct":null},{"date":"2026-01-04","opp":"WAS","result":"W, 141-115","pts":12,"reb":2,"ast":3,"stl":3,"blk":1,"tov":0,"tpm":0,"fg_pct":0.667,"ft_pct":0.8},{"date":"2026-01-06","opp":"MIA","result":"W, 122-94","pts":2,"reb":4,"ast":0,"stl":0,"blk":0,"tov":0,"tpm":0,"fg_pct":0,"ft_pct":1},{"date":"2026-01-08","opp":"CLE","result":"W, 131-122","pts":5,"reb":0,"ast":0,"stl":1,"blk":0,"tov":1,"tpm":1,"fg_pct":0.5,"ft_pct":null},{"date":"2026-01-10","opp":"CLE","result":"L, 134-146","pts":1,"reb":3,"ast":1,"stl":0,"blk":0,"tov":0,"tpm":0,"fg_pct":0,"ft_pct":0.5},{"date":"2026-01-11","opp":"SAS","result":"W, 104-103","pts":2,"reb":0,"ast":1,"stl":0,"blk":0,"tov":1,"tpm":0,"fg_pct":0.5,"ft_pct":null},{"date":"2026-01-13","opp":"MIL","result":"W, 139-106","pts":4,"reb":6,"ast":2,"stl":2,"blk":0,"tov":0,"tpm":0,"fg_pct":0.333,"ft_pct":null},{"date":"2026-01-16","opp":"HOU","result":"L, 105-110","pts":0,"reb":2,"ast":0,"stl":0,"blk":0,"tov":0,"tpm":0,"fg_pct":null,"ft_pct":null},{"date":"2026-01-17","opp":"SAS","result":"L, 123-126","pts":0,"reb":3,"ast":2,"stl":0,"blk":1,"tov":0,"tpm":0,"fg_pct":0,"ft_pct":null},{"date":"2026-01-20","opp":"UTA","result":"L, 122-127","pts":4,"reb":2,"ast":0,"stl":1,"blk":0,"tov":0,"tpm":0,"fg_pct":1,"ft_pct":null},{"date":"2026-01-22","opp":"CHI","result":"L, 115-120","pts":2,"reb":1,"ast":1,"stl":0,"blk":0,"tov":0,"tpm":0,"fg_pct":0.333,"ft_pct":null},{"date":"2026-01-25","opp":"GSW","result":"L, 85-111","pts":0,"reb":0,"ast":1,"stl":0,"blk":0,"tov":1,"tpm":0,"fg_pct":0,"ft_pct":null},{"date":"2026-01-26","opp":"GSW","result":"W, 108-83","pts":4,"reb":3,"ast":2,"stl":2,"blk":0,"tov":0,"tpm":0,"fg_pct":0.333,"ft_pct":1},{"date":"2026-01-28","opp":"DAL","result":"W, 118-105","pts":0,"reb":1,"ast":1,"stl":0,"blk":0,"tov":0,"tpm":0,"fg_pct":0,"ft_pct":null},{"date":"2026-01-29","opp":"OKC","result":"W, 123-111","pts":7,"reb":3,"ast":1,"stl":0,"blk":1,"tov":0,"tpm":1,"fg_pct":0.75,"ft_pct":null},{"date":"2026-01-31","opp":"MEM","result":"W, 131-114","pts":5,"reb":2,"ast":0,"stl":1,"blk":0,"tov":1,"tpm":0,"fg_pct":0.667,"ft_pct":1},{"date":"2026-02-02","opp":"MEM","result":"L, 128-137","pts":0,"reb":0,"ast":0,"stl":0,"blk":0,"tov":0,"tpm":0,"fg_pct":0,"ft_pct":null},{"date":"2026-02-04","opp":"TOR","result":"W, 128-126","pts":0,"reb":0,"ast":0,"stl":1,"blk":0,"tov":0,"tpm":0,"fg_pct":0,"ft_pct":0},{"date":"2026-02-06","opp":"NOP","result":"L, 115-119","pts":0,"reb":5,"ast":0,"stl":0,"blk":0,"tov":0,"tpm":0,"fg_pct":0,"ft_pct":null},{"date":"2026-02-08","opp":"LAC","result":"L, 96-115","pts":8,"reb":1,"ast":0,"stl":1,"blk":0,"tov":1,"tpm":1,"fg_pct":0.75,"ft_pct":0.333},{"date":"2026-02-09","opp":"ATL","result":"W, 138-116","pts":3,"reb":0,"ast":0,"stl":0,"blk":0,"tov":0,"tpm":1,"fg_pct":1,"ft_pct":null},{"date":"2026-02-11","opp":"POR","result":"W, 133-109","pts":5,"reb":2,"ast":1,"stl":2,"blk":0,"tov":1,"tpm":1,"fg_pct":0.5,"ft_pct":null},{"date":"2026-02-22","opp":"PHI","result":"L, 108-135","pts":2,"reb":1,"ast":0,"stl":0,"blk":0,"tov":1,"tpm":0,"fg_pct":0.333,"ft_pct":null},{"date":"2026-03-05","opp":"TOR","result":"W, 115-107","pts":0,"reb":0,"ast":0,"stl":0,"blk":0,"tov":0,"tpm":0,"fg_pct":0,"ft_pct":null},{"date":"2026-03-07","opp":"ORL","result":"L, 92-119","pts":0,"reb":0,"ast":0,"stl":0,"blk":0,"tov":0,"tpm":0,"fg_pct":0,"ft_pct":null},{"date":"2026-03-10","opp":"LAL","result":"L, 106-120","pts":5,"reb":0,"ast":0,"stl":0,"blk":0,"tov":0,"tpm":1,"fg_pct":1,"ft_pct":null},{"date":"2026-03-11","opp":"LAC","result":"L, 128-153","pts":11,"reb":0,"ast":1,"stl":0,"blk":0,"tov":0,"tpm":2,"fg_pct":0.8,"ft_pct":1},{"date":"2026-03-15","opp":"OKC","result":"L, 103-116","pts":0,"reb":1,"ast":0,"stl":0,"blk":0,"tov":0,"tpm":0,"fg_pct":0,"ft_pct":null},{"date":"2026-03-18","opp":"UTA","result":"W, 147-111","pts":9,"reb":2,"ast":0,"stl":0,"blk":0,"tov":0,"tpm":2,"fg_pct":0.429,"ft_pct":1},{"date":"2026-03-22","opp":"BOS","result":"W, 102-92","pts":0,"reb":3,"ast":2,"stl":0,"blk":0,"tov":1,"tpm":0,"fg_pct":null,"ft_pct":null},{"date":"2026-03-28","opp":"DET","result":"L, 87-109","pts":9,"reb":4,"ast":0,"stl":0,"blk":0,"tov":1,"tpm":0,"fg_pct":0.333,"ft_pct":0.833},{"date":"2026-03-30","opp":"DAL","result":"W, 124-94","pts":2,"reb":2,"ast":0,"stl":0,"blk":0,"tov":0,"tpm":0,"fg_pct":0.5,"ft_pct":null},{"date":"2026-04-05","opp":"CHO","result":"L, 108-122","pts":9,"reb":0,"ast":2,"stl":1,"blk":0,"tov":0,"tpm":3,"fg_pct":0.75,"ft_pct":null},{"date":"2026-04-07","opp":"IND","result":"W, 124-104","pts":11,"reb":1,"ast":0,"stl":4,"blk":0,"tov":0,"tpm":1,"fg_pct":0.556,"ft_pct":null},{"date":"2026-04-08","opp":"ORL","result":"L, 120-132","pts":3,"reb":2,"ast":4,"stl":2,"blk":0,"tov":0,"tpm":1,"fg_pct":0.167,"ft_pct":null},{"date":"2026-04-10","opp":"HOU","result":"W, 136-132","pts":2,"reb":1,"ast":1,"stl":1,"blk":0,"tov":1,"tpm":0,"fg_pct":1,"ft_pct":null},{"date":"2026-04-12","opp":"NOP","result":"W, 132-126","pts":8,"reb":3,"ast":2,"stl":0,"blk":1,"tov":1,"tpm":2,"fg_pct":0.333,"ft_pct":null}]