[{"date":"2025-10-26","opp":"WAS","result":"W, 139-113","pts":4,"reb":0,"ast":1,"stl":0,"blk":0,"tov":0,"tpm":0,"fg_pct":1,"ft_pct":0},{"date":"2025-10-30","opp":"ORL","result":"L, 107-123","pts":0,"reb":0,"ast":0,"stl":0,"blk":0,"tov":0,"tpm":0,"fg_pct":null,"ft_pct":null},{"date":"2025-11-02","opp":"UTA","result":"W, 126-103","pts":6,"reb":1,"ast":0,"stl":0,"blk":1,"tov":1,"tpm":2,"fg_pct":0.4,"ft_pct":null},{"date":"2025-11-04","opp":"NOP","result":"L, 112-116","pts":3,"reb":1,"ast":1,"stl":0,"blk":0,"tov":0,"tpm":1,"fg_pct":0.5,"ft_pct":null},{"date":"2025-11-07","opp":"MIA","result":"L, 108-126","pts":6,"reb":5,"ast":0,"stl":0,"blk":0,"tov":1,"tpm":0,"fg_pct":0.5,"ft_pct":1},{"date":"2025-11-10","opp":"LAL","result":"L, 111-121","pts":0,"reb":5,"ast":0,"stl":1,"blk":0,"tov":1,"tpm":0,"fg_pct":null,"ft_pct":null},{"date":"2025-11-12","opp":"MIL","result":"W, 111-100","pts":11,"reb":2,"ast":2,"stl":0,"blk":0,"tov":0,"tpm":2,"fg_pct":0.667,"ft_pct":0.5},{"date":"2025-11-14","opp":"MIL","result":"L, 134-147 (OT)","pts":0,"reb":0,"ast":1,"stl":2,"blk":0,"tov":0,"tpm":0,"fg_pct":0,"ft_pct":null},{"date":"2025-11-15","opp":"OKC","result":"L, 96-109","pts":3,"reb":4,"ast":1,"stl":1,"blk":0,"tov":0,"tpm":1,"fg_pct":0.25,"ft_pct":null},{"date":"2025-11-17","opp":"TOR","result":"L, 108-110","pts":5,"reb":1,"ast":0,"stl":0,"blk":0,"tov":0,"tpm":0,"fg_pct":0.5,"ft_pct":0.75},{"date":"2025-11-19","opp":"IND","result":"L, 118-127","pts":13,"reb":2,"ast":1,"stl":1,"blk":0,"tov":0,"tpm":3,"fg_pct":0.714,"ft_pct":null},{"date":"2025-11-22","opp":"LAC","result":"L, 116-131","pts":0,"reb":2,"ast":0,"stl":0,"blk":0,"tov":0,"tpm":0,"fg_pct":0,"ft_pct":null},{"date":"2025-12-20","opp":"DET","result":"L, 86-112","pts":0,"reb":0,"ast":0,"stl":0,"blk":0,"tov":0,"tpm":0,"fg_pct":null,"ft_pct":null},{"date":"2025-12-22","opp":"CLE","result":"L, 132-139","pts":3,"reb":2,"ast":0,"stl":0,"blk":0,"tov":0,"tpm":1,"fg_pct":1,"ft_pct":null},{"date":"2025-12-23","opp":"WAS","result":"W, 126-109","pts":0,"reb":0,"ast":0,"stl":0,"blk":0,"tov":0,"tpm":0,"fg_pct":null,"ft_pct":null},{"date":"2025-12-26","opp":"ORL","result":"W, 120-105","pts":1,"reb":0,"ast":1,"stl":0,"blk":0,"tov":0,"tpm":0,"fg_pct":null,"ft_pct":0.5},{"date":"2026-01-05","opp":"OKC","result":"W, 124-97","pts":0,"reb":0,"ast":1,"stl":0,"blk":0,"tov":0,"tpm":0,"fg_pct":null,"ft_pct":null},{"date":"2026-01-15","opp":"LAL","result":"W, 135-117","pts":0,"reb":1,"ast":0,"stl":0,"blk":0,"tov":0,"tpm":0,"fg_pct":null,"ft_pct":null},{"date":"2026-01-17","opp":"GSW","result":"L, 116-136","pts":5,"reb":1,"ast":0,"stl":0,"blk":0,"tov":0,"tpm":0,"fg_pct":0.5,"ft_pct":0.5},{"date":"2026-01-18","opp":"DEN","result":"W, 110-87","pts":3,"reb":1,"ast":3,"stl":0,"blk":0,"tov":0,"tpm":1,"fg_pct":0.5,"ft_pct":null},{"date":"2026-01-22","opp":"ORL","result":"W, 124-97","pts":0,"reb":0,"ast":1,"stl":0,"blk":0,"tov":0,"tpm":0,"fg_pct":0,"ft_pct":null},{"date":"2026-01-26","opp":"PHI","result":"W, 130-93","pts":0,"reb":2,"ast":1,"stl":0,"blk":0,"tov":0,"tpm":0,"fg_pct":null,"ft_pct":null},{"date":"2026-02-20","opp":"CLE","result":"L, 113-118","pts":5,"reb":5,"ast":1,"stl":0,"blk":0,"tov":2,"tpm":1,"fg_pct":0.667,"ft_pct":null},{"date":"2026-02-22","opp":"WAS","result":"W, 129-112","pts":2,"reb":3,"ast":0,"stl":0,"blk":0,"tov":0,"tpm":0,"fg_pct":0.333,"ft_pct":null},{"date":"2026-02-24","opp":"CHI","result":"W, 131-99","pts":5,"reb":3,"ast":0,"stl":0,"blk":0,"tov":1,"tpm":1,"fg_pct":0.286,"ft_pct":null},{"date":"2026-02-26","opp":"IND","result":"W, 133-109","pts":5,"reb":1,"ast":1,"stl":1,"blk":0,"tov":1,"tpm":0,"fg_pct":1,"ft_pct":1},{"date":"2026-02-28","opp":"POR","result":"W, 109-93","pts":0,"reb":0,"ast":0,"stl":0,"blk":0,"tov":1,"tpm":0,"fg_pct":null,"ft_pct":null},{"date":"2026-03-03","opp":"DAL","result":"W, 117-90","pts":8,"reb":2,"ast":0,"stl":0,"blk":0,"tov":1,"tpm":2,"fg_pct":0.667,"ft_pct":1},{"date":"2026-03-04","opp":"BOS","result":"W, 118-89","pts":6,"reb":2,"ast":1,"stl":1,"blk":0,"tov":0,"tpm":2,"fg_pct":0.286,"ft_pct":null},{"date":"2026-03-08","opp":"PHO","result":"L, 99-111","pts":0,"reb":1,"ast":0,"stl":0,"blk":0,"tov":0,"tpm":0,"fg_pct":0,"ft_pct":null},{"date":"2026-03-10","opp":"POR","result":"W, 103-101","pts":3,"reb":2,"ast":0,"stl":1,"blk":0,"tov":0,"tpm":1,"fg_pct":0.5,"ft_pct":null},{"date":"2026-03-11","opp":"SAC","result":"W, 117-109","pts":0,"reb":1,"ast":0,"stl":0,"blk":0,"tov":0,"tpm":0,"fg_pct":0,"ft_pct":null},{"date":"2026-03-17","opp":"MIA","result":"W, 136-106","pts":4,"reb":1,"ast":0,"stl":1,"blk":0,"tov":0,"tpm":1,"fg_pct":1,"ft_pct":0.5},{"date":"2026-03-19","opp":"ORL","result":"W, 130-111","pts":0,"reb":0,"ast":0,"stl":1,"blk":0,"tov":0,"tpm":0,"fg_pct":0,"ft_pct":null},{"date":"2026-03-21","opp":"MEM","result":"W, 124-101","pts":0,"reb":1,"ast":0,"stl":0,"blk":0,"tov":0,"tpm":0,"fg_pct":null,"ft_pct":null},{"date":"2026-03-29","opp":"BOS","result":"L, 99-114","pts":0,"reb":1,"ast":0,"stl":0,"blk":0,"tov":0,"tpm":0,"fg_pct":null,"ft_pct":null},{"date":"2026-03-31","opp":"BRK","result":"W, 117-86","pts":2,"reb":1,"ast":0,"stl":0,"blk":0,"tov":0,"tpm":0,"fg_pct":1,"ft_pct":null},{"date":"2026-04-02","opp":"PHO","result":"W, 127-107","pts":0,"reb":1,"ast":0,"stl":0,"blk":0,"tov":0,"tpm":0,"fg_pct":null,"ft_pct":null},{"date":"2026-04-03","opp":"IND","result":"W, 129-108","pts":7,"reb":3,"ast":1,"stl":1,"blk":0,"tov":1,"tpm":2,"fg_pct":0.5,"ft_pct":0.5},{"date":"2026-04-05","opp":"MIN","result":"W, 122-108","pts":0,"reb":2,"ast":0,"stl":0,"blk":0,"tov":0,"tpm":0,"fg_pct":null,"ft_pct":null},{"date":"2026-04-07","opp":"BOS","result":"L, 102-113","pts":0,"reb":1,"ast":0,"stl":0,"blk":0,"tov":0,"tpm":0,"fg_pct":0,"ft_pct":null},{"date":"2026-04-10","opp":"DET","result":"L, 100-118","pts":0,"reb":0,"ast":0,"stl":0,"blk":0,"tov":1,"tpm":0,"fg_pct":0,"ft_pct":null}]