[{"date":"2026-03-11","opp":"NYK","result":"L, 117-134","pts":6,"reb":9,"ast":0,"stl":1,"blk":1,"tov":1,"tpm":0,"fg_pct":0.4,"ft_pct":1},{"date":"2026-03-13","opp":"POR","result":"L, 114-124","pts":6,"reb":3,"ast":2,"stl":2,"blk":0,"tov":3,"tpm":0,"fg_pct":0.333,"ft_pct":1},{"date":"2026-03-15","opp":"SAC","result":"L, 111-116","pts":3,"reb":11,"ast":3,"stl":2,"blk":1,"tov":2,"tpm":1,"fg_pct":0.143,"ft_pct":null},{"date":"2026-03-18","opp":"MIN","result":"L, 111-147","pts":4,"reb":8,"ast":3,"stl":0,"blk":2,"tov":0,"tpm":0,"fg_pct":0.2,"ft_pct":1},{"date":"2026-03-19","opp":"MIL","result":"W, 128-96","pts":7,"reb":11,"ast":6,"stl":3,"blk":0,"tov":1,"tpm":0,"fg_pct":0.5,"ft_pct":0.333}]